qbittorrentui/__init__.py
qbittorrentui/__main__.py
qbittorrentui/config.py
qbittorrentui/connector.py
qbittorrentui/daemon.py
qbittorrentui/debug.py
qbittorrentui/default.ini
qbittorrentui/events.py
qbittorrentui/formatters.py
qbittorrentui/main.py
qbittorrentui/misc_widgets.py
qbittorrentui/_vendored/__init__.py
qbittorrentui/_vendored/_directions.txt
qbittorrentui/_vendored/attrdict.py
qbittorrentui/windows/__init__.py
qbittorrentui/windows/application.py
qbittorrentui/windows/torrent.py
qbittorrentui/windows/torrent_list.py
qbittorrentui-0.3.6.dist-info/LICENSE
qbittorrentui-0.3.6.dist-info/METADATA
qbittorrentui-0.3.6.dist-info/WHEEL
qbittorrentui-0.3.6.dist-info/entry_points.txt
qbittorrentui-0.3.6.dist-info/top_level.txt
qbittorrentui-0.3.6.dist-info/RECORD
