Metadata-Version: 2.1
Name: qbittorrentui
Version: 0.3.6
Summary: Console UI for qBittorrent v4.1+
Author: Russell Martin
Maintainer: Russell Martin
Project-URL: Homepage, https://github.com/rmartin16/qbittorrentui
Project-URL: Source, https://github.com/rmartin16/qbittorrentui
Keywords: qbittorrent,console,terminal,TUI,text
Classifier: Environment :: Console
Classifier: License :: OSI Approved :: MIT License
Classifier: Topic :: Communications :: File Sharing
Classifier: Topic :: Utilities
Classifier: Programming Language :: Python :: 3
Classifier: Programming Language :: Python :: 3.8
Classifier: Programming Language :: Python :: 3.9
Classifier: Programming Language :: Python :: 3.10
Classifier: Programming Language :: Python :: 3.11
Classifier: Programming Language :: Python :: 3.12
Classifier: Programming Language :: Python :: 3.13
Classifier: Programming Language :: Python :: 3 :: Only
Classifier: Programming Language :: Python :: Implementation :: CPython
Requires-Python: >=3.8
License-File: LICENSE
Requires-Dist: qbittorrent-api
Requires-Dist: urwid==2.6.16
Requires-Dist: blinker==1.8.2
Requires-Dist: panwid==0.3.5
Provides-Extra: dev
Requires-Dist: pre-commit; extra == "dev"
Requires-Dist: tox; extra == "dev"
